{
  "name": "Multipage poster",
  "nodes": [
    {
      "parameters": {
        "fieldToSplitOut": "data",
        "options": {}
      },
      "type": "n8n-nodes-base.splitOut",
      "typeVersion": 1,
      "position": [
        -960,
        -1168
      ],
      "id": "49749826-5c36-452d-9c90-37486c4cde12",
      "name": "Split Out"
    },
    {
      "parameters": {
        "url": "https://graph.facebook.com/v19.0/me/accounts",
        "sendQuery": true,
        "queryParameters": {
          "parameters": [
            {
              "name": "access_token",
              "value": ""
            }
          ]
        },
        "options": {}
      },
      "type": "n8n-nodes-base.httpRequest",
      "typeVersion": 4.4,
      "position": [
        -1184,
        -1056
      ],
      "id": "1d820223-3264-4333-b7d6-83191b402e0d",
      "name": "HTTP Request_1"
    },
    {
      "parameters": {
        "method": "POST",
        "url": "=https://graph.facebook.com/v19.0/{{$json[\"page_id\"]}}/feed",
        "sendQuery": true,
        "queryParameters": {
          "parameters": [
            {
              "name": "message",
              "value": "={{ $json.message }}"
            },
            {
              "name": "access_token",
              "value": "={{ $json.page_token }}"
            }
          ]
        },
        "options": {}
      },
      "type": "n8n-nodes-base.httpRequest",
      "typeVersion": 4.4,
      "position": [
        -576,
        -1008
      ],
      "id": "55473571-3690-4efe-8227-8ba1f9d98f2a",
      "name": "HTTP Request_2"
    },
    {
      "parameters": {
        "assignments": {
          "assignments": [
            {
              "id": "7de8a06f-5224-43b4-8a5d-c6587e7e9baf",
              "name": "page_id",
              "value": "={{ $json.id }}",
              "type": "string"
            },
            {
              "id": "e987581f-faf8-4390-950e-12a041cce659",
              "name": "page_token",
              "value": "={{ $json.access_token }}",
              "type": "string"
            },
            {
              "id": "1eb19dca-a036-4562-8b8e-21bb1f71c773",
              "name": "message",
              "value": "Your message here",
              "type": "string"
            }
          ]
        },
        "options": {}
      },
      "type": "n8n-nodes-base.set",
      "typeVersion": 3.4,
      "position": [
        -752,
        -1120
      ],
      "id": "5ff4b9af-a470-493c-8907-518117832d85",
      "name": "Edit Fields1"
    },
    {
      "parameters": {
        "rule": {
          "interval": [
            {}
          ]
        }
      },
      "type": "n8n-nodes-base.scheduleTrigger",
      "typeVersion": 1.3,
      "position": [
        -1440,
        -1056
      ],
      "id": "6015bf49-66d5-4f79-93c3-07da8cb5d1c8",
      "name": "Schedule Trigger"
    }
  ],
  "pinData": {},
  "connections": {
    "Split Out": {
      "main": [
        [
          {
            "node": "Edit Fields1",
            "type": "main",
            "index": 0
          }
        ]
      ]
    },
    "HTTP Request_1": {
      "main": [
        [
          {
            "node": "Split Out",
            "type": "main",
            "index": 0
          }
        ]
      ]
    },
    "HTTP Request_2": {
      "main": [
        []
      ]
    },
    "Edit Fields1": {
      "main": [
        [
          {
            "node": "HTTP Request_2",
            "type": "main",
            "index": 0
          }
        ]
      ]
    },
    "Schedule Trigger": {
      "main": [
        [
          {
            "node": "HTTP Request_1",
            "type": "main",
            "index": 0
          }
        ]
      ]
    }
  },
  "active": false,
  "settings": {
    "executionOrder": "v1",
    "binaryMode": "separate",
    "availableInMCP": false
  },
  "tags": []
}